cronster/__init__.py
cronster/crawler.py
cronster/scheduler.py
cronster-0.1.1.dist-info/DESCRIPTION.rst
cronster-0.1.1.dist-info/LICENSE.txt
cronster-0.1.1.dist-info/METADATA
cronster-0.1.1.dist-info/RECORD
cronster-0.1.1.dist-info/WHEEL
cronster-0.1.1.dist-info/entry_points.txt
cronster-0.1.1.dist-info/metadata.json
cronster-0.1.1.dist-info/top_level.txt
