Metadata-Version: 2.0
Name: cronster
Version: 0.1.1
Summary: Crawl filesystems for crontab files and schedule jobs.
Home-page: https://github.com/florianeinfalt/cronster
Author: Florian Einfalt
Author-email: info@florianeinfalt.de
License: Apache 2.0
Platform: UNKNOWN
Classifier: Development Status :: 3 - Alpha
Classifier: Intended Audience :: Developers
Classifier: Natural Language :: English
Classifier: Topic :: Software Development :: Build Tools
Classifier: License :: OSI Approved :: Apache Software License
Classifier: Programming Language :: Python
Classifier: Programming Language :: Python :: 3
Classifier: Programming Language :: Python :: 3.5
Classifier: Programming Language :: Python :: 3.6
Classifier: Programming Language :: Python :: Implementation :: CPython
Requires-Dist: croniter
Requires-Dist: click
Requires-Dist: PyYaml
Requires-Dist: redis
Requires-Dist: tabulate
